libloader/__init__.py
libloader/com.py
libloader/libloader.py
bp_lib_loader-0.22.dist-info/LICENSE
bp_lib_loader-0.22.dist-info/METADATA
bp_lib_loader-0.22.dist-info/WHEEL
bp_lib_loader-0.22.dist-info/top_level.txt
bp_lib_loader-0.22.dist-info/RECORD
